wificitylogin.py
wificitylogin-1.0.1.dist-info/entry_points.txt
wificitylogin-1.0.1.dist-info/LICENSE
wificitylogin-1.0.1.dist-info/WHEEL
wificitylogin-1.0.1.dist-info/METADATA
wificitylogin-1.0.1.dist-info/RECORD
