Metadata-Version: 2.1
Name: wificitylogin
Version: 1.0.1
Summary: Automated login to the CIUP's Ethernet and Wi-Fi networks.
Home-page: https://github.com/maxmouchet/wificitylogin
License: MIT
Author: Maxime Mouchet
Author-email: max@maxmouchet.com
Requires-Python: >=3.6.1,<4.0.0
Classifier: License :: OSI Approved :: MIT License
Classifier: Programming Language :: Python :: 3
Classifier: Programming Language :: Python :: 3.10
Classifier: Programming Language :: Python :: 3.7
Classifier: Programming Language :: Python :: 3.8
Classifier: Programming Language :: Python :: 3.9
Requires-Dist: beautifulsoup4 (>=4.10.0,<5.0.0)
Requires-Dist: requests (>=2.27.0,<3.0.0)
